tgcrypto.cpython-311-darwin.so
tests/__init__.py
tests/ige/__init__.py
tests/ige/test_ige.py
tests/ctr/__init__.py
tests/ctr/test_ctr.py
tests/cbc/__init__.py
tests/cbc/test_cbc.py
ElectroCrypto-1.1.0.dist-info/RECORD
ElectroCrypto-1.1.0.dist-info/WHEEL
ElectroCrypto-1.1.0.dist-info/COPYING.lesser
ElectroCrypto-1.1.0.dist-info/NOTICE
ElectroCrypto-1.1.0.dist-info/COPYING
ElectroCrypto-1.1.0.dist-info/top_level.txt
ElectroCrypto-1.1.0.dist-info/METADATA
